arttoascii/__init__.py
arttoascii/functions.py
art_to_ascii-1.0.0.dist-info/LICENCE.txt
art_to_ascii-1.0.0.dist-info/METADATA
art_to_ascii-1.0.0.dist-info/WHEEL
art_to_ascii-1.0.0.dist-info/top_level.txt
art_to_ascii-1.0.0.dist-info/RECORD
